ratisbona_utils/__init__.py
ratisbona_utils/__main__.py
ratisbona_utils/example.py
ratisbona_utils/abstractdrawing/__init__.py
ratisbona_utils/abstractdrawing/abstract_drawing.py
ratisbona_utils/arrays/__init__.py
ratisbona_utils/arrays/_d2array.py
ratisbona_utils/arrays/_d2array_serde.py
ratisbona_utils/arrays/_slices.py
ratisbona_utils/asyncio/__init__.py
ratisbona_utils/asyncio/_process_runner.py
ratisbona_utils/binary/__init__.py
ratisbona_utils/binary/binary_tools.py
ratisbona_utils/binary/utf8.py
ratisbona_utils/boxdrawing/__init__.py
ratisbona_utils/boxdrawing/_boxdrawing.py
ratisbona_utils/click_extensions/__init__.py
ratisbona_utils/click_extensions/_click_extensions.py
ratisbona_utils/colors/__init__.py
ratisbona_utils/colors/__main__.py
ratisbona_utils/colors/good_palettes.py
ratisbona_utils/colors/matplotlib.py
ratisbona_utils/colors/palette.py
ratisbona_utils/colors/palette_cli.py
ratisbona_utils/colors/palette_generators.py
ratisbona_utils/colors/serde_gimp.py
ratisbona_utils/colors/serde_json_palette.py
ratisbona_utils/colors/serde_python_source.py
ratisbona_utils/colors/simple_color.py
ratisbona_utils/colors/resources/OptWare.json
ratisbona_utils/colors/resources/__init__.py
ratisbona_utils/colors/resources/commodore64.json
ratisbona_utils/colors/resources/viridis32.json
ratisbona_utils/combinatorics/__init__.py
ratisbona_utils/combinatorics/_permutations.py
ratisbona_utils/compression/__init__.py
ratisbona_utils/datetime/__init__.py
ratisbona_utils/datetime/_date_parser.py
ratisbona_utils/datetime/_date_tokenizer.py
ratisbona_utils/datetime/_datetime_utils.py
ratisbona_utils/datetime/_ddate.py
ratisbona_utils/datetime/_gaussian_easter.py
ratisbona_utils/datetime/_stopwatch.py
ratisbona_utils/functional/__init__.py
ratisbona_utils/functional/_functional.py
ratisbona_utils/images/__init__.py
ratisbona_utils/images/image_encoding.py
ratisbona_utils/images/imagecache.py
ratisbona_utils/intervals/__init__.py
ratisbona_utils/intervals/_interval.py
ratisbona_utils-0.0.4.dist-info/METADATA
ratisbona_utils-0.0.4.dist-info/WHEEL
ratisbona_utils-0.0.4.dist-info/entry_points.txt
ratisbona_utils-0.0.4.dist-info/licenses/LICENSE
ratisbona_utils-0.0.4.dist-info/RECORD
