Metadata-Version: 2.4
Name: ratisbona_utils
Version: 0.0.4
Summary: A package comprising various utilities useful for many python projects.
Project-URL: Homepage, https://sourceforge.net/projects/ratisbona-utils/
Author-email: Ulrich Schwenk <ulrich-schwenk@gmx.de>
License-File: LICENSE
Classifier: License :: OSI Approved :: GNU Lesser General Public License v3 (LGPLv3)
Classifier: Operating System :: OS Independent
Classifier: Programming Language :: Python :: 3
Requires-Python: >=3.9
Requires-Dist: asyncio
Requires-Dist: click
Requires-Dist: graphviz
Requires-Dist: matplotlib
Requires-Dist: pathlib
Requires-Dist: python-magic
Requires-Dist: transliterate
Requires-Dist: tzdata
Requires-Dist: unidecode
Provides-Extra: dev
Requires-Dist: black[d]; extra == 'dev'
Requires-Dist: build; extra == 'dev'
Requires-Dist: coverage; extra == 'dev'
Requires-Dist: mypy; extra == 'dev'
Requires-Dist: poethepoet; extra == 'dev'
Requires-Dist: pylint; extra == 'dev'
Requires-Dist: pytest; extra == 'dev'
Requires-Dist: twine; extra == 'dev'
